sockaddr/__init__.py
sockaddr/addr.py
sockaddr/util.py
sockaddr-0.1.3.dist-info/LICENSE
sockaddr-0.1.3.dist-info/WHEEL
sockaddr-0.1.3.dist-info/METADATA
sockaddr-0.1.3.dist-info/RECORD
