Metadata-Version: 2.1
Name: sockaddr
Version: 0.1.3
Summary: Prepopulated sockaddr helpers for Python using ctypes
Keywords: sockaddr,saddr,auditd
Author-email: tedk <tedk@kpn-cert.nl>
Classifier: License :: OSI Approved :: GNU General Public License v3 or later (GPLv3+)
Classifier: Development Status :: 3 - Alpha
Classifier: Intended Audience :: Developers
Classifier: Programming Language :: Python :: 3
Classifier: Topic :: Internet :: Log Analysis
Classifier: Topic :: Security
Classifier: Topic :: System :: Networking
Project-URL: Github, https://github.com/Kalkran/sockaddr
